wltrace/TODO.rst
wltrace/__init__.py
wltrace/__init__.pyc
wltrace/common.py
wltrace/dot11.py
wltrace/fusion.py
wltrace/pcap.py
wltrace/peektagged.py
wltrace/quality.py
wltrace/radiotap.py
wltrace/utils.py
wltrace/wltrace.py
wltrace-1.0.7.dist-info/DESCRIPTION.rst
wltrace-1.0.7.dist-info/METADATA
wltrace-1.0.7.dist-info/RECORD
wltrace-1.0.7.dist-info/WHEEL
wltrace-1.0.7.dist-info/metadata.json
wltrace-1.0.7.dist-info/top_level.txt
