Metadata-Version: 2.0
Name: wltrace
Version: 1.0.7
Summary: A Python library to parse Pcap (w/ Radtiotap) and Peektagged packet traces.
Home-page: https://github.com/jhshi/wltrace
Author: Jinghao Shi
Author-email: jhshi89@gmail.com
License: UNKNOWN
Download-URL: https://github.com/jhshi/wltrace/tarball/1.0.7
Keywords: pcap,radiotap,peektagged,trace
Platform: UNKNOWN
Classifier: Development Status :: 3 - Alpha
Classifier: Environment :: Console
Classifier: Intended Audience :: Developers
Classifier: License :: OSI Approved :: Apache Software License
Classifier: Operating System :: POSIX :: Linux
Classifier: Programming Language :: Python :: 2.7
Classifier: Topic :: System :: Networking :: Monitoring
Requires-Dist: numpy (>=1.10)
Requires-Dist: progressbar (>=2.3)
Requires-Dist: python-dateutil (>=2.5.3)
